{"intents": [
        {"tag": "greeting",
         "patterns": ["Hi there", "How are you", "Is anyone there?","Hey","Hola", "Hello", "Good day"],
         "responses": ["Hello there", "Hola", "Hi bot", "Good day", "It's good to see you", "Hi! How's it going?", "Hi there, how can I help?"],
         "context": [""]
        },
        {"tag": "inspiration",
        "patterns": [],
        "responses": ["Have a great day!", "Nothing is impossible, the word itself says I'm possible! Just go ahead!", "We all are special we just need to find our specialty.", "The only way to do great work is to love what you do. - Steve Jobs", "Believe you can and you are halfway there. - Theodore Roosevelt"],
        "context": [""]
        },
        {"tag": "goodbye",
         "patterns": ["Bye", "See you later", "Goodbye", "Nice chatting to you, bye", "Till next time"],
         "responses": ["See you!", "Have a nice day", "Bye! Come back again soon."],
         "context": [""]
        },
        {"tag": "thanks",
         "patterns": ["Thanks", "Thank you", "That's helpful", "Awesome, thanks", "Thanks for helping me"],
         "responses": ["Happy to help!", "Any time!", "My pleasure"],
         "context": [""]
        },
        {"tag": "noanswer",
         "patterns": [],
         "responses": ["Sorry, can't understand you", "Please give me more info", "Not sure I understand"],
         "context": [""]
        },
        {"tag": "eating",
        "patterns": ["I am hungry", "hungry", "I want to eat something", "I need food", "food"],
        "responses": ["Maybe, you should have a brunch", "Try healthy yogurt if you like", "Hmm, get some healthy snacks", "A boiled egg is a good choice", "Let's go to boost energy with some snakcs."],
        "context": [""]
        },
        {"tag": "what_to_eat",
        "patterns": ["No, it's not enough", "I dont like to eat that", "what should I eat for breakfast?", "what should I eat for lunch?", "what should I eat for dinner?", "what should I cook today?", "Can you suggest something to eat?", "No, I want more", "I wanna cook something"],
        "responses": ["Healthy salad is a good choice", "How about pasta?", "You like sandwich with smoked bacon, egg & mayonaise?", "Chicken nuggets with fries & salad", "You want some Yangzhou fried rice & juice", "I think you should try Simmered Pork in fish sauce with pepper & Young tofu soup", "Some healthy dishes like steamed chicken & tomato soup"],
        "context": [""]
        },
        {"tag": "drink",
        "patterns": ["I would like to drink something now", "Can you suggest something to drink?", "Anything to drink", "I hate water"],
        "responses":["Orange juice with much Vitamin C is super great for your heath this time", "Try milk juice? there are many flavors", "Do not think of soft drink like coke anymore, you should drink juice", "How about smoothies?  If you have some fruit at home, try now", "Maybe a cup of coffee if you feel asleep", "Try a cup of tea with lemon, really fresh!"],
        "context": [""]
        },
        {"tag": "where_buy_drink",
        "patterns":  ["how to buy drink?", "how can I buy them?", "due to covid, I cannot go out to buy easily", "can you suggest where to buy drink?", "It's hard hard to buy now, so how can I make healthy drinks?", "how to make that?"],
        "responses": ["I think you should by online and check some recepies on Google", "You should buy online on Grab or Now and then try making by yourself! I'm sure it is easy", "Let's check on Grab or Now for some fresh fruits and keep them in your refrigerator. You can make everytime you want"],
        "context": [""]
        },
        {"tag": "options",
         "patterns": ["How you could help me?", "What you can do?", "What help you provide?", "How you can be helpful?", "What support is offered"],
         "responses": ["I can guide you through Adverse drug reaction list, Blood pressure tracking, Hospitals and Pharmacies", "Offering support for Adverse drug reaction, Blood pressure, Hospitals and Pharmacies"],
         "context": [""]
        },
        {"tag": "adverse_drug",
         "patterns": ["How to check Adverse drug reaction?", "Open adverse drugs module", "Give me a list of drugs causing adverse behavior", "List all drugs suitable for patient with adverse reaction", "Which drugs dont have adverse reaction?" ],
         "responses": ["Navigating to Adverse drug reaction module"],
         "context": [""]
        },
        {"tag": "blood_pressure",
         "patterns": ["Open blood pressure module", "Task related to blood pressure", "Blood pressure data entry", "I want to log blood pressure results", "Blood pressure data management" ],
         "responses": ["Navigating to Blood Pressure module"],
         "context": [""]
        },
        {"tag": "blood_pressure_search",
         "patterns": ["I want to search for blood pressure result history", "Blood pressure for patient", "Load patient blood pressure result", "Show blood pressure results for patient", "Find blood pressure results by ID" ],
         "responses": ["Please provide Patient ID", "Patient ID?"],
         "context": ["search_blood_pressure_by_patient_id"]
        },
        {"tag": "search_blood_pressure_by_patient_id",
         "patterns": [],
         "responses": ["Loading Blood pressure result for Patient"],
         "context": [""]
        },
        {"tag": "pharmacy_search",
         "patterns": ["Find me a pharmacy", "Find pharmacy", "List of pharmacies nearby", "Locate pharmacy", "Search pharmacy" ],
         "responses": ["Please provide pharmacy name"],
         "context": ["search_pharmacy_by_name"]
        },
        {"tag": "search_pharmacy_by_name",
         "patterns": [],
         "responses": ["Loading pharmacy details"],
         "context": [""]
        },
        {"tag": "hospital_search",
         "patterns": ["Lookup for hospital", "Searching for hospital to transfer patient", "I want to search hospital data", "Hospital lookup for patient", "Looking up hospital details" ],
         "responses": ["Please provide hospital name or location"],
         "context": ["search_hospital_by_params"]
        },
        {"tag": "search_hospital_by_params",
         "patterns": [],
         "responses": ["Please provide hospital type"],
         "context": ["search_hospital_by_type"]
        },
        {"tag": "search_hospital_by_type",
         "patterns": [],
         "responses": ["Loading hospital details"],
         "context": [""]
        },
        {"tag": "birthday",
        "patterns": [],
        "responses": ["Today is your birthday, I wish you have a wonderful day!", "Happy birthday! I hope all your birthday wishes and dreams come true", "May the joy that you have spread in the past come back to you on this day. Wishing you a very happy birthday!", "Count not the candles…see the lights they give. Count not the years, but the life you live. Wishing you a wonderful time ahead. Happy birthday.", "Your birthday is the first day of another 365-day journey. Be the shining thread in the beautiful tapestry of the world to make this year the best ever. Enjoy the ride.", "A birthday is like a new year and my wish for you, is a great year full of happiness and sunshine!", "May your birthday be sprinkled with fun and laughter. Have a great day!"],
        "context": [""]
        },
        {"tag": "christmas",
        "patterns": [],
        "responses": ["Merry Christmas to you and your family", "Let us keep Christmas beautiful without a thought of greed.", "It's the season to wish one another joy, love and peace. These are my wishes for you. Merry Christmas, my dear friend. May you feel the love this special day brings.", "You make the stars shine brighter and the winter days warmer just by being in my life. Merry Christmas to my favourite person in the world", "May the joy and peace that comes with Christmas be with you all through the Year. I wish you a season of blessings from heaven above"],
        "context": [""]
        },
        {"tag": "work_aniversary",
        "patterns": [],
        "responses": ["Congratulations on your work milestone at Hitachi Vantara Vietnam, thank you for all your hardwork", "Happy Work Anniversary! Another year of excellence! Thanks for all the amazing work you do. Your effort and enthusiasm are much needed, and very much appreciated.", "Happy work anniversary! They are truly lucky to have such a smart, thoughtful, and talented person like you" ],
        "context": [""]
        },
        {"tag": "drink_water",
        "patterns": [],
        "responses": ["Let's have a sip of water, it's good for your health", "Hi, a kind reminder for a drinking water. Hurry!", "Your body told me that it really needs water! Drink now"],
        "context": [""]
        },
        {"tag": "stand_up",
        "patterns": [],
        "responses": ["You should stand up for a little while, it's good for your health"],
        "context": [""]
        },
        {"tag": "walk",
        "patterns": [],
        "responses": ["You should walk around a litle bit, it's good for your health"],
        "context": [""]
        },
        {"tag": "do_exercise",
        "patterns": [],
        "responses": ["You should do a small exercise, it's good for your health"],
        "context": [""]
        },
        {"tag": "ask_employee",
        "patterns": [],
        "responses": ["How do you feel today?"],
        "context": [""]
        },
        {"tag": "answer_good",
        "patterns": ["good", "best", "terrific", "today is good", "it is terrific", "better", "this is the best day", "awesome", "delightful", "nice"],
        "responses": ["Thank you for your response. I'm glad that you're having a good day."],
        "context": [""]
        },
        {"tag": "answer_neutral",
        "patterns": ["normal", "neutral", "today is normal", "it is neutral", "same day", "as usual"],
        "responses": ["Thank you for your response. I'm having a feeling that tomorrow is going to be nice."],
        "context": [""]
        },
        {"tag": "answer_bad",
        "patterns": ["bad", "worse", "worst", "today is bad", "it is terrible", "worse", "this is the worst day", "not good", "I'm tired today", "boring"],
        "responses": ["Thank you for your response. I'm sorry to hear that, tomorrow is going to be a brand new awesome day, trust me."],
        "context": [""]
        }
   ]
}
